listarray2ndarray/LICENSE
listarray2ndarray/README.MD
listarray2ndarray/__init__.py
listarray2ndarray/requirements.txt
listarray2ndarray/thirdparty.json
listarray2ndarray-0.10.dist-info/LICENSE.rst
listarray2ndarray-0.10.dist-info/METADATA
listarray2ndarray-0.10.dist-info/WHEEL
listarray2ndarray-0.10.dist-info/top_level.txt
listarray2ndarray-0.10.dist-info/RECORD
