Metadata-Version: 2.1
Name: listarray2ndarray
Version: 0.10
Summary: Converts a list of numpy arrays to a ndarray
Home-page: https://github.com/hansalemaos/listarray2ndarray
Author: Johannes Fischer
Author-email: <aulasparticularesdealemaosp@gmail.com>
License: MIT
Keywords: numpy,list,convert
Classifier: Development Status :: 4 - Beta
Classifier: Programming Language :: Python :: 3 :: Only
Classifier: Programming Language :: Python :: 3.9
Classifier: Topic :: Scientific/Engineering :: Visualization
Classifier: Topic :: Software Development :: Libraries :: Python Modules
Classifier: Topic :: Text Editors :: Text Processing
Classifier: Topic :: Text Processing :: General
Classifier: Topic :: Text Processing :: Indexing
Classifier: Topic :: Text Processing :: Filters
Classifier: Topic :: Utilities
License-File: LICENSE.rst
Requires-Dist: flatten-everything
Requires-Dist: numpy
Requires-Dist: tolerant-isinstance
